{"name":"Characters","imagePath":"mainChar_tex.png","SubTexture":[{"frameWidth":190,"y":1,"frameHeight":307,"width":189,"frameX":-1,"height":249,"name":"c13","frameY":-29,"x":1},{"frameWidth":190,"y":675,"frameHeight":307,"width":174,"frameX":-8,"height":170,"name":"c8","frameY":-68,"x":485},{"frameWidth":154,"y":675,"frameHeight":307,"width":103,"frameX":-26,"height":281,"name":"c2","frameY":-13,"x":661},{"frameWidth":190,"y":1,"frameHeight":307,"width":190,"frameX":0,"height":214,"name":"c11","frameY":-46,"x":192},{"frameWidth":190,"y":252,"frameHeight":307,"width":190,"frameX":0,"height":232,"name":"c12","frameY":-37,"x":1},{"frameWidth":156,"y":675,"frameHeight":307,"width":156,"frameX":0,"height":184,"name":"c7","frameY":-61,"x":766},{"frameWidth":154,"y":217,"frameHeight":307,"width":128,"frameX":-13,"height":214,"name":"c5","frameY":-46,"x":193},{"frameWidth":154,"y":675,"frameHeight":307,"width":148,"frameX":-3,"height":203,"name":"c6","frameY":-52,"x":335},{"frameWidth":154,"y":217,"frameHeight":307,"width":103,"frameX":-26,"height":253,"name":"c3","frameY":-27,"x":323},{"frameWidth":160,"y":1,"frameHeight":320,"width":114,"frameX":-23,"height":222,"name":"c1","frameY":-48,"x":533},{"frameWidth":158,"y":675,"frameHeight":256,"width":148,"frameX":-5,"height":221,"name":"c14","frameY":-17,"x":1},{"frameWidth":190,"y":486,"frameHeight":307,"width":190,"frameX":0,"height":187,"name":"c10","frameY":-59,"x":1},{"frameWidth":154,"y":433,"frameHeight":307,"width":110,"frameX":-22,"height":232,"name":"c4","frameY":-37,"x":193},{"frameWidth":190,"y":675,"frameHeight":307,"width":182,"frameX":-4,"height":178,"name":"c9","frameY":-64,"x":151},{"frameWidth":190,"y":217,"frameHeight":307,"width":103,"frameX":-44,"height":253,"name":"c2-2","frameY":-27,"x":428}]}